Classfile /W:/code/algorithm/gh/src/main/java/lang/abasic/AnnotationRetentionTest.class
  Last modified 2020-6-29; size 504 bytes
  MD5 checksum 210c13a539823a53bf27ccc41ec43a95
  Compiled from "AnnotationRetentionTest.java"
public class sssdnsy.abasic.AnnotationRetentionTest
  minor version: 0
  major version: 52
  flags: ACC_PUBLIC, ACC_SUPER
Constant pool:
   #1 = Methodref          #3.#17         // java/lang/Object."<init>":()V
   #2 = Class              #18            // lang/abasic/AnnotationRetentionTest
   #3 = Class              #19            // java/lang/Object
   #4 = Class              #20            // lang/abasic/AnnotationRetentionTest$RuntimeRetention
   #5 = Utf8               RuntimeRetention
   #6 = Utf8               InnerClasses
   #7 = Class              #21            // lang/abasic/AnnotationRetentionTest$ClassRetention
   #8 = Utf8               ClassRetention
   #9 = Class              #22            // lang/abasic/AnnotationRetentionTest$SourceRetention
  #10 = Utf8               SourceRetention
  #11 = Utf8               <init>
  #12 = Utf8               ()V
  #13 = Utf8               Code
  #14 = Utf8               LineNumberTable
  #15 = Utf8               SourceFile
  #16 = Utf8               AnnotationRetentionTest.java
  #17 = NameAndType        #11:#12        // "<init>":()V
  #18 = Utf8               lang/abasic/AnnotationRetentionTest
  #19 = Utf8               java/lang/Object
  #20 = Utf8               lang/abasic/AnnotationRetentionTest$RuntimeRetention
  #21 = Utf8               lang/abasic/AnnotationRetentionTest$ClassRetention
  #22 = Utf8               lang/abasic/AnnotationRetentionTest$SourceRetention
{
  public sssdnsy.abasic.AnnotationRetentionTest();
    descriptor: ()V
    flags: ACC_PUBLIC
    Code:
      stack=1, locals=1, args_size=1
         0: aload_0
         1: invokespecial #1                  // Method java/lang/Object."<init>":()V
         4: return
      LineNumberTable:
        line 10: 0
}
SourceFile: "AnnotationRetentionTest.java"
InnerClasses:
     static #5= #4 of #2; //RuntimeRetention=class lang/abasic/AnnotationRetentionTest$RuntimeRetention of class lang/abasic/AnnotationRetentionTest
     static #8= #7 of #2; //ClassRetention=class lang/abasic/AnnotationRetentionTest$ClassRetention of class lang/abasic/AnnotationRetentionTest
     static #10= #9 of #2; //SourceRetention=class lang/abasic/AnnotationRetentionTest$SourceRetention of class lang/abasic/AnnotationRetentionTest
